LICENSE.txt
MANIFEST.in
README.md
pyproject.toml
setup.py
num2fa/__about__.py
num2fa/__init__.py
num2fa/cli.py
num2fa/constants.py
num2fa/utils.py
num2fa.egg-info/PKG-INFO
num2fa.egg-info/SOURCES.txt
num2fa.egg-info/dependency_links.txt
num2fa.egg-info/entry_points.txt
num2fa.egg-info/requires.txt
num2fa.egg-info/top_level.txt
num2fa/converters/__init__.py
num2fa/converters/number_converter.py
num2fa/converters/word_converter.py
requirements/base.in
requirements/base.txt
requirements/dev.txt
tests/test_numbers.py
tests/test_words.py