Metadata-Version: 2.1
Name: num2fa
Version: 0.1.16
Summary: A library to convert numbers (ints, floats, and other standard numerical types) into Persian numbers or words.
Author: Emad Rad
Author-email: codewithemad@gmail.com
License: AGPLv3
Project-URL: Code, https://github.com/iranian-github/num2fa
Project-URL: Issue tracker, https://github.com/iranian-github/num2fa/issues
Classifier: Development Status :: 4 - Beta
Classifier: Intended Audience :: Developers
Classifier: License :: OSI Approved :: MIT License
Classifier: Programming Language :: Python :: 3.6
Classifier: Programming Language :: Python :: 3.7
Classifier: Programming Language :: Python :: 3.8
Classifier: Programming Language :: Python :: 3.9
Classifier: Programming Language :: Python :: 3.10
Classifier: Programming Language :: Python :: 3.11
Classifier: Programming Language :: Python :: 3.12
Requires-Python: >=3.6
License-File: LICENSE.txt
Requires-Dist: click==8.1.7
Provides-Extra: dev
Requires-Dist: attrs==23.1.0; extra == "dev"
Requires-Dist: black==23.12.1; extra == "dev"
Requires-Dist: build==1.0.3; extra == "dev"
Requires-Dist: certifi==2023.11.17; extra == "dev"
Requires-Dist: cffi==1.16.0; extra == "dev"
Requires-Dist: charset-normalizer==3.3.2; extra == "dev"
Requires-Dist: click==8.1.7; extra == "dev"
Requires-Dist: click-log==0.4.0; extra == "dev"
Requires-Dist: cryptography==41.0.7; extra == "dev"
Requires-Dist: docutils==0.20.1; extra == "dev"
Requires-Dist: exceptiongroup==1.2.0; extra == "dev"
Requires-Dist: idna==3.6; extra == "dev"
Requires-Dist: importlib-metadata==7.0.1; extra == "dev"
Requires-Dist: iniconfig==2.0.0; extra == "dev"
Requires-Dist: jaraco-classes==3.3.0; extra == "dev"
Requires-Dist: jeepney==0.8.0; extra == "dev"
Requires-Dist: jinja2==3.1.2; extra == "dev"
Requires-Dist: keyring==24.3.0; extra == "dev"
Requires-Dist: markdown-it-py==3.0.0; extra == "dev"
Requires-Dist: markupsafe==2.1.3; extra == "dev"
Requires-Dist: mdurl==0.1.2; extra == "dev"
Requires-Dist: more-itertools==10.1.0; extra == "dev"
Requires-Dist: mypy-extensions==1.0.0; extra == "dev"
Requires-Dist: nh3==0.2.15; extra == "dev"
Requires-Dist: packaging==23.2; extra == "dev"
Requires-Dist: pathspec==0.12.1; extra == "dev"
Requires-Dist: pip-tools==7.3.0; extra == "dev"
Requires-Dist: pkginfo==1.9.6; extra == "dev"
Requires-Dist: platformdirs==4.1.0; extra == "dev"
Requires-Dist: pluggy==1.3.0; extra == "dev"
Requires-Dist: pycparser==2.21; extra == "dev"
Requires-Dist: pygments==2.17.2; extra == "dev"
Requires-Dist: pyproject-hooks==1.0.0; extra == "dev"
Requires-Dist: pytest==7.4.3; extra == "dev"
Requires-Dist: readme-renderer==42.0; extra == "dev"
Requires-Dist: requests==2.31.0; extra == "dev"
Requires-Dist: requests-toolbelt==1.0.0; extra == "dev"
Requires-Dist: rfc3986==2.0.0; extra == "dev"
Requires-Dist: rich==13.7.0; extra == "dev"
Requires-Dist: scriv==1.5.1; extra == "dev"
Requires-Dist: secretstorage==3.3.3; extra == "dev"
Requires-Dist: tomli==2.0.1; extra == "dev"
Requires-Dist: twine==4.0.2; extra == "dev"
Requires-Dist: typing-extensions==4.9.0; extra == "dev"
Requires-Dist: urllib3==2.1.0; extra == "dev"
Requires-Dist: wheel==0.42.0; extra == "dev"
Requires-Dist: zipp==3.17.0; extra == "dev"
